dictionary/__init__.py
dictionary/dictionary.py
f4f4_dictionary-3.0.0.dist-info/METADATA
f4f4_dictionary-3.0.0.dist-info/WHEEL
f4f4_dictionary-3.0.0.dist-info/top_level.txt
f4f4_dictionary-3.0.0.dist-info/RECORD
